{
	"configurations" : 
	[
		{
			"directories" : 
			[
				{
					"build" : ".",
					"hasInstallRule" : true,
					"jsonFile" : "directory-.-Debug-b02736a077e6e54ee31a.json",
					"minimumCMakeVersion" : 
					{
						"string" : "3.15"
					},
					"projectIndex" : 0,
					"source" : ".",
					"targetIndexes" : 
					[
						0
					]
				}
			],
			"name" : "Debug",
			"projects" : 
			[
				{
					"directoryIndexes" : 
					[
						0
					],
					"name" : "TDK",
					"targetIndexes" : 
					[
						0
					]
				}
			],
			"targets" : 
			[
				{
					"directoryIndex" : 0,
					"id" : "tdk::@6890427a1f51a3e7e1df",
					"jsonFile" : "target-tdk-Debug-39ef2fd98e70d0122d89.json",
					"name" : "tdk",
					"projectIndex" : 0
				}
			]
		}
	],
	"kind" : "codemodel",
	"paths" : 
	{
		"build" : "/Users/kevebotos/Documents/cpp/TDK/cmake-build-debug",
		"source" : "/Users/kevebotos/Documents/cpp/TDK"
	},
	"version" : 
	{
		"major" : 2,
		"minor" : 7
	}
}
